<dashboard>
  <label>Index Monitor</label>
  <row>
    <panel>
      <title>Index Status</title>
      <table>
        <search>
          <query>| savedsearch lsm_analyse_indexes 
| eval type="index"
| lookup lsm_application_lookup indicator AS Index,type output application
| fields - type
| rename application AS Application
| sort - Status</query>
          <earliest>0</earliest>
          <latest></latest>
          <sampleRatio>1</sampleRatio>
        </search>
        <option name="count">20</option>
        <option name="dataOverlayMode">none</option>
        <option name="drilldown">cell</option>
        <option name="percentagesRow">false</option>
        <option name="refresh.display">progressbar</option>
        <option name="rowNumbers">false</option>
        <option name="totalsRow">false</option>
        <option name="wrap">true</option>
        <format type="color" field="Status">
          <colorPalette type="map">{"ok":#B6C75A,"outage":#DC4E41,"underload":#F8BE34,"overload":#F1813F}</colorPalette>
        </format>
        <drilldown>
          <set token="index">$row.Index$</set>
        </drilldown>
      </table>
    </panel>
    <panel>
      <title>Missing indexes</title>
      <table>
        <search>
          <query>| savedsearch lsm_missing_indexes</query>
          <earliest>-24h@h</earliest>
          <latest>now</latest>
          <sampleRatio>1</sampleRatio>
        </search>
        <option name="count">20</option>
        <option name="dataOverlayMode">none</option>
        <option name="drilldown">none</option>
        <option name="percentagesRow">false</option>
        <option name="refresh.display">progressbar</option>
        <option name="rowNumbers">false</option>
        <option name="totalsRow">false</option>
        <option name="wrap">true</option>
      </table>
    </panel>
  </row>
  <row>
    <panel depends="$index$">
      <title>Sourcetypes of $index$</title>
      <table>
        <search>
          <query>| `lsm_analyse_sourcetype($index$)`</query>
          <earliest>-24h@h</earliest>
          <latest>now</latest>
          <sampleRatio>1</sampleRatio>
        </search>
        <option name="count">20</option>
        <option name="dataOverlayMode">none</option>
        <option name="drilldown">cell</option>
        <option name="percentagesRow">false</option>
        <option name="refresh.display">progressbar</option>
        <option name="rowNumbers">false</option>
        <option name="totalsRow">false</option>
        <option name="wrap">true</option>
        <format type="color" field="Status">
          <colorPalette type="map">{"ok":#B6C75A,"outage":#DC4E41,"underload":#F8BE34,"overload":#F1813F}</colorPalette>
        </format>
        <drilldown>
          <set token="index">$row.Index$</set>
          <set token="sourcetype">$row.Sourcetype$</set>
        </drilldown>
      </table>
    </panel>
  </row>
  <row>
    <panel depends="$sourcetype$">
      <title>Sources of $index$ / $sourcetype$</title>
      <table>
        <search>
          <query>| `lsm_analyse_source($index$,*,$sourcetype$)`</query>
          <earliest>1</earliest>
          <latest>1566900512</latest>
          <sampleRatio>1</sampleRatio>
        </search>
        <option name="count">20</option>
        <option name="dataOverlayMode">none</option>
        <option name="drilldown">cell</option>
        <option name="percentagesRow">false</option>
        <option name="refresh.display">progressbar</option>
        <option name="rowNumbers">false</option>
        <option name="totalsRow">false</option>
        <option name="wrap">true</option>
        <format type="color" field="Status">
          <colorPalette type="map">{"ok":#B6C75A,"outage":#DC4E41,"underload":#F8BE34,"overload":#F1813F}</colorPalette>
        </format>
        <drilldown>
          <link target="_blank">search?q=index=*%20host=%22$row.Host$%22%20source=%22$row.Source$%22&amp;earliest=-24h&amp;latest=now</link>
        </drilldown>
      </table>
    </panel>
  </row>
</dashboard>
